tiefeng/__init__.py
tiefeng/common/__init__.py
tiefeng/common/enums/__init__.py
tiefeng/common/enums/api_enums.py
tiefeng/common/enums/dict_enum_decorator.py
tiefeng/common/enums/enum_items.py
tiefeng/common/exception/__init__.py
tiefeng/common/exception/error_code.py
tiefeng/common/schemas/__init__.py
tiefeng/common/schemas/base_schemas.py
tiefeng/common/schemas/response_schemas.py
tiefeng/container/__init__.py
tiefeng/container/docker/__init__.py
tiefeng/container/docker/docker_service.py
tiefeng/container/docker/docker_swarm_service.py
tiefeng/db/__init__.py
tiefeng/db/common/__init__.py
tiefeng/db/common/schemas/__init__.py
tiefeng/db/common/schemas/page_schemas.py
tiefeng/db/common/tools/__init__.py
tiefeng/db/common/tools/db_type_tools.py
tiefeng/db/sqlalchemy/__init__.py
tiefeng/db/sqlalchemy/base.py
tiefeng/db/sqlalchemy/base_models.py
tiefeng/db/sqlalchemy/crud_tools.py
tiefeng/fs/__init__.py
tiefeng/fs/ipfs/__init__.py
tiefeng/fs/ipfs/ipfs_client_service.py
tiefeng/fs/ipfs/ipfs_public_service.py
tiefeng/fs/ipfs/ipfs_service.py
tiefeng/fs/minio/__init__.py
tiefeng/fs/minio/minio_service.py
tiefeng/id/__init__.py
tiefeng/id/code_generator.py
tiefeng/id/id_code_tools.py
tiefeng/id/uuid_tools.py
tiefeng/log/__init__.py
tiefeng/log/logging_utils.py
tiefeng/web/__init__.py
tiefeng/web/common/__init__.py
tiefeng/web/common/util/__init__.py
tiefeng/web/common/util/url_path_utils.py
tiefeng/web/fastapi/__init__.py
tiefeng/web/fastapi/auth/__init__.py
tiefeng/web/fastapi/auth/auth_depends.py
tiefeng/web/fastapi/middleware/__init__.py
tiefeng/web/fastapi/middleware/auth_middleware.py
tiefeng/web/fastapi/middleware/bearer_auth_middleware.py
tiefeng_tools-0.1.0.4.dist-info/licenses/LICENSE
tiefeng_tools-0.1.0.4.dist-info/METADATA
tiefeng_tools-0.1.0.4.dist-info/WHEEL
tiefeng_tools-0.1.0.4.dist-info/RECORD
