Metadata-Version: 2.4
Name: tiefeng-tools
Version: 0.1.0.4
Summary: 铁锋的工具箱
License: GPLv3
License-File: LICENSE
Author: chentiefeng
Author-email: imchentiefeng@aliyun.com
Requires-Python: >=3.10
Classifier: Programming Language :: Python :: 3
Classifier: Operating System :: OS Independent
Project-URL: Homepage, https://gitee.com/python-playing/tiefeng-tools
Project-URL: Issues, https://gitee.com/python-playing/tiefeng-tools/issues
